<schema name="net.sourceforge.fenixedu.domain.ExecutionPeriod.edit" type="net.sourceforge.fenixedu.domain.ExecutionPeriod">
	<slot name="name"/>
	<slot name="semester" bundle="MANAGER_RESOURCES" key="label.semester"/>
	<slot name="beginDateYearMonthDay" bundle="MANAGER_RESOURCES" key="label.date.begin"/>
	<slot name="endDateYearMonthDay" bundle="MANAGER_RESOURCES" key="label.date.end"/>
</schema>
<schema name="net.sourceforge.fenixedu.domain.ExecutionYear.view" type="net.sourceforge.fenixedu.domain.ExecutionYear">
	<slot name="year" key="executionYear"/>
</schema>
<schema name="net.sourceforge.fenixedu.domain.ExecutionDegree.annotation" type="net.sourceforge.fenixedu.domain.ExecutionDegree">
	<slot name="anotation"/>
</schema>
<schema name="executionDegree.context.choose" type="net.sourceforge.fenixedu.dataTransferObject.administrativeOffice.ExecutionDegreeBean">
	<slot name="executionDegree" layout="menu-select-postback" key="label.executionDegree.year">
        <property name="providerClass" value="net.sourceforge.fenixedu.presentationTier.renderers.providers.executionDegree.ExecutionDegreesForDegreeCurricularPlan"/>
        <property name="format" value="${executionYear.year}"/>
        <property name="destination" value="chooseExecutionDegree"/>
    </slot>
</schema>
<schema name="executionDegree.context.choose.noNull" type="net.sourceforge.fenixedu.dataTransferObject.administrativeOffice.ExecutionDegreeBean">
	<slot name="executionDegree" layout="menu-select-postback" key="label.executionDegree.year">
        <property name="providerClass" value="net.sourceforge.fenixedu.presentationTier.renderers.providers.executionDegree.ExecutionDegreesForDegreeCurricularPlan"/>
        <property name="format" value="${executionYear.year}"/>
        <property name="destination" value="chooseExecutionDegree"/>
        <property name="nullOptionHidden" value="true"/>
    </slot>
</schema>

